rats/annotations/__init__.py
rats/annotations/__main__.py
rats/annotations/_functions.py
rats/annotations/py.typed
rats/app_context/__init__.py
rats/app_context/_collection.py
rats/app_context/_container.py
rats/app_context/_context.py
rats/app_context/py.typed
rats/apps/__init__.py
rats/apps/_annotations.py
rats/apps/_app_containers.py
rats/apps/_composite_container.py
rats/apps/_container.py
rats/apps/_executables.py
rats/apps/_ids.py
rats/apps/_mains.py
rats/apps/_namespaces.py
rats/apps/_plugin_container.py
rats/apps/_runtimes.py
rats/apps/_scoping.py
rats/apps/_static_container.py
rats/apps/py.typed
rats/cli/__init__.py
rats/cli/__main__.py
rats/cli/_annotations.py
rats/cli/_click_app.py
rats/cli/_command.py
rats/cli/_container.py
rats/cli/_functions.py
rats/cli/_plugin.py
rats/cli/py.typed
rats/logs/__init__.py
rats/logs/_app.py
rats/logs/_showwarning.py
rats/logs/py.typed
rats/runtime/__init__.py
rats/runtime/__main__.py
rats/runtime/_app.py
rats/runtime/_request.py
rats/runtime/py.typed
rats_e2e/apps/__init__.py
rats_e2e/apps/__main__.py
rats_e2e/apps/_example_cli.py
rats_e2e/apps/inputs/__init__.py
rats_e2e/apps/inputs/__main__.py
rats_e2e/apps/inputs/_app.py
rats_e2e/apps/minimal/__init__.py
rats_e2e/apps/minimal/__main__.py
rats_e2e/apps/minimal/_app.py
rats_e2e/apps/py.typed
rats_e2e/runtime/__init__.py
rats_e2e/runtime/_app.py
rats_e2e/runtime/_data.py
rats_e2e/runtime/py.typed
rats_resources/runtime/__init__.py
rats_resources/runtime/example-context.yaml
rats_apps-0.16.0.dist-info/WHEEL
rats_apps-0.16.0.dist-info/entry_points.txt
rats_apps-0.16.0.dist-info/METADATA
rats_apps-0.16.0.dist-info/RECORD
