Metadata-Version: 2.4
Name: rats-apps
Version: 0.16.0
Summary: research analysis tools for building applications
Keywords: pipelines,machine learning,research
Author: Elon Portugaly, Javier Zazo, Lorenzo Pisani
Author-email: Elon Portugaly <elonp@microsoft.com>, Javier Zazo <javierzazo@microsoft.com>, Lorenzo Pisani <lopisani@microsoft.com>
License-Expression: MIT
Requires-Dist: typing-extensions
Requires-Dist: click
Requires-Dist: pyyaml
Requires-Dist: dataclass-wizard
Requires-Dist: colorlog
Requires-Python: >=3.10, <4.0
Project-URL: repository, https://github.com/microsoft/rats
Project-URL: documentation, https://microsoft.github.io/rats
